flood_fill_filter/__init__.py
flood_fill_filter/__main__.py
flood_fill_filter/flood.py
flood_fill_filter/flood_test.py
flood_fill_filter/linear_srgb_conv.py
flood_fill_filter/linear_srgb_conv_test.py
flood_fill_filter/private/__init__.py
flood_fill_filter/private/calculations.py
flood_fill_filter/private/calculations_test.py
flood_fill_filter/private/xyz.py
flood_fill_filter/private/xyz_loader.py
flood_fill_filter-1.2.5.dist-info/COPYING
flood_fill_filter-1.2.5.dist-info/METADATA
flood_fill_filter-1.2.5.dist-info/WHEEL
flood_fill_filter-1.2.5.dist-info/entry_points.txt
flood_fill_filter-1.2.5.dist-info/top_level.txt
flood_fill_filter-1.2.5.dist-info/zip-safe
flood_fill_filter-1.2.5.dist-info/RECORD
