Metadata-Version: 2.1
Name: flood-fill-filter
Version: 1.2.5
Summary: JPEG-noise resistant edge density detection tool.
Home-page: https://github.com/georgy7/flood_fill_filter
Author: Georgy Ustinov
Author-email: georgy.ustinov.hello@gmail.com
License: AGPL-3.0-or-later
Platform: UNKNOWN
Classifier: Programming Language :: Python
Classifier: Programming Language :: Python :: 3.5
Classifier: Programming Language :: Python :: 3.6
Classifier: Programming Language :: Python :: 3.7
Classifier: Programming Language :: Python :: 3.8
Requires-Python: >=3.3
Requires-Dist: pillow
Requires-Dist: numpy
